dongraphio/__init__.py
dongraphio/base_models/__init__.py
dongraphio/base_models/grapher_logic.py
dongraphio/base_models/isochrones_logic.py
dongraphio/base_models/matrix_logic.py
dongraphio/dongraphio.py
dongraphio/enums.py
dongraphio/utils/__init__.py
dongraphio/utils/geometry_utils.py
dongraphio/utils/graph_utils.py
dongraphio/utils/matrix_utils.py
dongraphio/utils/osm_worker.py
dongraphio/utils/tsp_solver.py
dongraphio-0.3.14.dist-info/LICENSE.txt
dongraphio-0.3.14.dist-info/METADATA
dongraphio-0.3.14.dist-info/WHEEL
dongraphio-0.3.14.dist-info/RECORD
