Metadata-Version: 2.1
Name: dongraphio
Version: 0.3.14
Summary: Small utility library containing graph algorighms used in other projects
License: BSD-3-Clause
Author: Danila
Author-email: 63115678+DDonnyy@users.noreply.github.com
Requires-Python: >=3.10,<4.0
Classifier: License :: OSI Approved :: BSD License
Classifier: Programming Language :: Python :: 3
Classifier: Programming Language :: Python :: 3.10
Classifier: Programming Language :: Python :: 3.11
Classifier: Programming Language :: Python :: 3.12
Requires-Dist: geopandas (>=0.14.3,<0.15.0)
Requires-Dist: loguru (>=0.7.2,<0.8.0)
Requires-Dist: networkit (>=11.0,<12.0)
Requires-Dist: networkx (>=3.3,<4.0)
Requires-Dist: numpy (>=1.23.5,<2.0.0)
Requires-Dist: osm2geojson (>=0.2.4,<0.3.0)
Requires-Dist: osmnx (>=1.9.1,<2.0.0)
Requires-Dist: pandas (>=2.2.0,<3.0.0)
Requires-Dist: pydantic (>=2.6.1,<3.0.0)
Requires-Dist: scipy (>=1.13.1,<2.0.0)
Requires-Dist: tqdm (>=4.66.2,<5.0.0)
